lptypes/__init__.py
lptypes/goto.py
lptypes/lpython.py
lptypes-0.0.1.dist-info/LICENSE
lptypes-0.0.1.dist-info/METADATA
lptypes-0.0.1.dist-info/WHEEL
lptypes-0.0.1.dist-info/top_level.txt
lptypes-0.0.1.dist-info/RECORD
